odoo10_addon_l10n_ch_pain_base-10.0.1.1.1-py3.8-nspkg.pth
odoo/addons/l10n_ch_pain_base/README.rst
odoo/addons/l10n_ch_pain_base/__init__.py
odoo/addons/l10n_ch_pain_base/__manifest__.py
odoo/addons/l10n_ch_pain_base/i18n/de.po
odoo/addons/l10n_ch_pain_base/i18n/fr.po
odoo/addons/l10n_ch_pain_base/i18n/it.po
odoo/addons/l10n_ch_pain_base/i18n/l10n_ch_pain_base.pot
odoo/addons/l10n_ch_pain_base/i18n/nb_NO.po
odoo/addons/l10n_ch_pain_base/models/__init__.py
odoo/addons/l10n_ch_pain_base/models/account_move_line.py
odoo/addons/l10n_ch_pain_base/models/account_payment_line.py
odoo/addons/l10n_ch_pain_base/models/account_payment_order.py
odoo/addons/l10n_ch_pain_base/static/description/icon.png
odoo/addons/l10n_ch_pain_base/views/account_payment_line.xml
odoo/addons/l10n_ch_pain_base/views/bank_payment_line.xml
odoo10_addon_l10n_ch_pain_base-10.0.1.1.1.dist-info/METADATA
odoo10_addon_l10n_ch_pain_base-10.0.1.1.1.dist-info/WHEEL
odoo10_addon_l10n_ch_pain_base-10.0.1.1.1.dist-info/namespace_packages.txt
odoo10_addon_l10n_ch_pain_base-10.0.1.1.1.dist-info/top_level.txt
odoo10_addon_l10n_ch_pain_base-10.0.1.1.1.dist-info/RECORD
