Metadata-Version: 2.1
Name: odoo10-addon-l10n-ch-pain-base
Version: 10.0.1.1.1
Summary: ISO 20022 base module for Switzerland
Home-page: UNKNOWN
Author: Akretion,Camptocamp,Odoo Community Association (OCA)
Author-email: support@odoo-community.org
License: AGPL-3
Platform: UNKNOWN
Classifier: Programming Language :: Python
Classifier: Framework :: Odoo
Classifier: Framework :: Odoo :: 10.0
Classifier: License :: OSI Approved :: GNU Affero General Public License v3
Requires-Python: ~=2.7
Requires-Dist: odoo10-addon-account-banking-pain-base
Requires-Dist: odoo10-addon-l10n-ch-base-bank
Requires-Dist: odoo (<10.1dev,>=10.0)
